{"script":"100012","des":"主线12：鉴赏进修","exps":[{"para":{"tag":"tag_1"},"key":"tag"},{"para":{"cz":"特效"},"key":"tag"},{"para":{"cz":"音效"},"key":"tag"},{"para":{"cz":"前层立绘消失"},"key":"tag"},{"para":{"cz":"前层背景消失"},"key":"tag"},{"para":{"cz":"当前层背景出现"},"key":"tag"},{"para":{"trans":false,"alpha":0,"scaleX":1,"y":0,"scaleY":1,"img":"shiwusuo","mirrow":false,"bright":1,"layer":"bg","x":0},"key":"setLayer"},{"para":{"trans":false,"alpha":1,"scaleX":1,"y":0,"scaleY":1,"img":"shiwusuo","mirrow":false,"transTime":0,"bright":1,"layer":"bg","x":0},"key":"moveLayer"},{"para":{"cz":"当前层立绘出现"},"key":"tag"},{"para":{"cz":"语音播放"},"key":"tag"},{"para":{"cz":"文字播放"},"key":"tag"},{"para":{"cz":"等待"},"key":"tag"},{"para":{"tag":"tag_2"},"key":"tag"},{"para":{"cz":"特效"},"key":"tag"},{"para":{"cz":"音效"},"key":"tag"},{"para":{"channel":"bgm","volume":1,"loop":true,"snd":"richang"},"key":"playSound"},{"para":{"cz":"前层立绘消失"},"key":"tag"},{"para":{"cz":"前层背景消失"},"key":"tag"},{"para":{"cz":"当前层背景出现"},"key":"tag"},{"para":{"trans":true,"alpha":1,"scaleX":1,"y":0,"scaleY":1,"img":"shiwusuo","mirrow":false,"transTime":500,"bright":0.9,"layer":"bg","x":0},"key":"moveLayer"},{"para":{"time":500},"key":"wait"},{"para":{"cz":"当前层立绘出现"},"key":"tag"},{"para":{"trans":true,"alpha":0,"scaleX":1,"y":40,"scaleY":1,"img":"nanzhu_YJmiantan","mirrow":false,"bright":1,"layer":"chara2","x":272},"key":"setLayer"},{"para":{"trans":true,"alpha":1,"scaleX":1,"y":40,"scaleY":1,"img":"nanzhu_YJmiantan","mirrow":false,"transTime":500,"bright":1,"layer":"chara2","x":272},"key":"moveLayer"},{"para":{"time":500},"key":"wait"},{"para":{"cz":"语音播放"},"key":"tag"},{"para":{"cz":"文字播放"},"key":"tag"},{"para":{"nameSide":"right","charaName":"苏子轩","text":"[show]任务勉强完成了，恭喜你获得一星头衔，[color=ff0000]【初入星途】[color=835133]，解锁了一星任务，[color=ff0000]你的头衔越高所解锁的任务等级越高，获得的魅力值也就越高，[color=835133]明白了吗？[l][hide][cm]"},"key":"text"},{"para":{"cz":"等待"},"key":"tag"},{"para":{"tag":"tag_3"},"key":"tag"},{"para":{"cz":"特效"},"key":"tag"},{"para":{"cz":"音效"},"key":"tag"},{"para":{"cz":"前层立绘消失"},"key":"tag"},{"para":{"cz":"前层背景消失"},"key":"tag"},{"para":{"cz":"当前层背景出现"},"key":"tag"},{"para":{"trans":false,"alpha":1,"scaleX":1,"y":0,"scaleY":1,"img":"shiwusuo","mirrow":false,"transTime":0,"bright":0.9,"layer":"bg","x":0},"key":"moveLayer"},{"para":{"cz":"当前层立绘出现"},"key":"tag"},{"para":{"trans":true,"alpha":1,"scaleX":1,"y":40,"scaleY":1,"img":"nanzhu_YJmiantan","mirrow":false,"transTime":500,"bright":0.95,"layer":"chara2","x":480},"key":"moveLayer"},{"para":{"trans":true,"alpha":0,"scaleX":1,"y":128,"scaleY":1,"img":"huaiyi","mirrow":false,"bright":1,"layer":"chara1","x":49},"key":"setLayer"},{"para":{"trans":true,"alpha":1,"scaleX":1,"y":128,"scaleY":1,"img":"huaiyi","mirrow":false,"transTime":500,"bright":1,"layer":"chara1","x":49},"key":"moveLayer"},{"para":{"time":500},"key":"wait"},{"para":{"cz":"语音播放"},"key":"tag"},{"para":{"cz":"文字播放"},"key":"tag"},{"para":{"nameSide":"left","charaName":"{nvzhuName}","text":"[show]勉强完成是指？[l][hide][cm]"},"key":"text"},{"para":{"cz":"等待"},"key":"tag"},{"para":{"tag":"tag_5"},"key":"tag"},{"para":{"cz":"特效"},"key":"tag"},{"para":{"cz":"音效"},"key":"tag"},{"para":{"cz":"前层立绘消失"},"key":"tag"},{"para":{"cz":"前层背景消失"},"key":"tag"},{"para":{"cz":"当前层背景出现"},"key":"tag"},{"para":{"cz":"当前层立绘出现"},"key":"tag"},{"para":{"trans":false,"alpha":1,"scaleX":1,"y":40,"scaleY":1,"img":"nanzhu_YJmiantan","mirrow":false,"transTime":0,"bright":0.95,"layer":"chara2","x":480},"key":"moveLayer"},{"para":{"trans":false,"alpha":1,"scaleX":1,"y":128,"scaleY":1,"img":"huaiyi","mirrow":false,"transTime":0,"bright":1,"layer":"chara1","x":49},"key":"moveLayer"},{"para":{"cz":"语音播放"},"key":"tag"},{"para":{"cz":"文字播放"},"key":"tag"},{"para":{"cz":"等待"},"key":"tag"},{"para":{"tag":"tag_4"},"key":"tag"},{"para":{"cz":"特效"},"key":"tag"},{"para":{"cz":"音效"},"key":"tag"},{"para":{"cz":"前层立绘消失"},"key":"tag"},{"para":{"trans":false,"alpha":0,"scaleX":1,"y":40,"scaleY":1,"img":"nanzhu_YJmiantan","mirrow":false,"transTime":0,"bright":0.95,"layer":"chara2","x":480},"key":"moveLayer"},{"para":{"cz":"前层背景消失"},"key":"tag"},{"para":{"cz":"当前层背景出现"},"key":"tag"},{"para":{"cz":"当前层立绘出现"},"key":"tag"},{"para":{"trans":false,"alpha":0,"scaleX":1,"y":40,"scaleY":1,"img":"nanzhu_YJbiyan","mirrow":false,"bright":1,"layer":"chara2","x":480},"key":"setLayer"},{"para":{"trans":false,"alpha":1,"scaleX":1,"y":40,"scaleY":1,"img":"nanzhu_YJbiyan","mirrow":false,"transTime":0,"bright":1,"layer":"chara2","x":480},"key":"moveLayer"},{"para":{"trans":false,"alpha":1,"scaleX":1,"y":128,"scaleY":1,"img":"huaiyi","mirrow":false,"transTime":0,"bright":0.95,"layer":"chara1","x":49},"key":"moveLayer"},{"para":{"cz":"语音播放"},"key":"tag"},{"para":{"cz":"文字播放"},"key":"tag"},{"para":{"nameSide":"right","charaName":"苏子轩","text":"[show]如果你听不懂委婉的话，我可以直接一些，我对你的完成度不是很满意，作为一个新人，你需要学的还有很多。[l][hide][cm]"},"key":"text"},{"para":{"cz":"等待"},"key":"tag"},{"para":{"tag":"tag_6"},"key":"tag"},{"para":{"cz":"特效"},"key":"tag"},{"para":{"cz":"音效"},"key":"tag"},{"para":{"cz":"前层立绘消失"},"key":"tag"},{"para":{"trans":false,"alpha":0,"scaleX":1,"y":128,"scaleY":1,"img":"huaiyi","mirrow":false,"transTime":0,"bright":0.95,"layer":"chara1","x":49},"key":"moveLayer"},{"para":{"cz":"前层背景消失"},"key":"tag"},{"para":{"cz":"当前层背景出现"},"key":"tag"},{"para":{"cz":"当前层立绘出现"},"key":"tag"},{"para":{"trans":false,"alpha":1,"scaleX":1,"y":40,"scaleY":1,"img":"nanzhu_YJbiyan","mirrow":false,"transTime":0,"bright":0.95,"layer":"chara2","x":480},"key":"moveLayer"},{"para":{"trans":false,"alpha":0,"scaleX":1,"y":120,"scaleY":1,"img":"ganga","mirrow":false,"bright":1,"layer":"chara1","x":68},"key":"setLayer"},{"para":{"trans":false,"alpha":1,"scaleX":1,"y":120,"scaleY":1,"img":"ganga","mirrow":false,"transTime":0,"bright":1,"layer":"chara1","x":68},"key":"moveLayer"},{"para":{"cz":"语音播放"},"key":"tag"},{"para":{"cz":"文字播放"},"key":"tag"},{"para":{"nameSide":"left","charaName":"{nvzhuName}","text":"[show]抱歉，秀场的衣物太多，我有几套搭配混乱了，还好及时发现了……[l][hide][cm]"},"key":"text"},{"para":{"cz":"等待"},"key":"tag"},{"para":{"tag":"tag_13"},"key":"tag"},{"para":{"cz":"特效"},"key":"tag"},{"para":{"cz":"音效"},"key":"tag"},{"para":{"cz":"前层立绘消失"},"key":"tag"},{"para":{"trans":false,"alpha":0,"scaleX":1,"y":40,"scaleY":1,"img":"nanzhu_YJbiyan","mirrow":false,"transTime":0,"bright":0.95,"layer":"chara2","x":480},"key":"moveLayer"},{"para":{"cz":"前层背景消失"},"key":"tag"},{"para":{"cz":"当前层背景出现"},"key":"tag"},{"para":{"cz":"当前层立绘出现"},"key":"tag"},{"para":{"trans":false,"alpha":0,"scaleX":1,"y":40,"scaleY":1,"img":"nanzhu_YJbanlian","mirrow":false,"bright":1,"layer":"chara2","x":480},"key":"setLayer"},{"para":{"trans":false,"alpha":1,"scaleX":1,"y":40,"scaleY":1,"img":"nanzhu_YJbanlian","mirrow":false,"transTime":0,"bright":1,"layer":"chara2","x":480},"key":"moveLayer"},{"para":{"trans":false,"alpha":1,"scaleX":1,"y":120,"scaleY":1,"img":"ganga","mirrow":false,"transTime":0,"bright":0.95,"layer":"chara1","x":68},"key":"moveLayer"},{"para":{"cz":"语音播放"},"key":"tag"},{"para":{"cz":"文字播放"},"key":"tag"},{"para":{"nameSide":"right","charaName":"苏子轩","text":"[show]另外，你现在到商城购物，老板娘会提供些一般人买不到的商品，你的头衔越响亮，提供的服装就越高级。[l]你如果一直这么平庸，是配不上那些高档的衣服的。[l][hide][cm]"},"key":"text"},{"para":{"cz":"等待"},"key":"tag"},{"para":{"tag":"tag_14"},"key":"tag"},{"para":{"cz":"特效"},"key":"tag"},{"para":{"cz":"音效"},"key":"tag"},{"para":{"cz":"前层立绘消失"},"key":"tag"},{"para":{"trans":false,"alpha":0,"scaleX":1,"y":120,"scaleY":1,"img":"ganga","mirrow":false,"transTime":0,"bright":0.95,"layer":"chara1","x":68},"key":"moveLayer"},{"para":{"cz":"前层背景消失"},"key":"tag"},{"para":{"cz":"当前层背景出现"},"key":"tag"},{"para":{"cz":"当前层立绘出现"},"key":"tag"},{"para":{"trans":false,"alpha":1,"scaleX":1,"y":40,"scaleY":1,"img":"nanzhu_YJbanlian","mirrow":false,"transTime":0,"bright":0.95,"layer":"chara2","x":480},"key":"moveLayer"},{"para":{"trans":false,"alpha":0,"scaleX":1,"y":128,"scaleY":1,"img":"nuli","mirrow":false,"bright":1,"layer":"chara1","x":49},"key":"setLayer"},{"para":{"trans":false,"alpha":1,"scaleX":1,"y":128,"scaleY":1,"img":"nuli","mirrow":false,"transTime":0,"bright":1,"layer":"chara1","x":49},"key":"moveLayer"},{"para":{"cz":"语音播放"},"key":"tag"},{"para":{"cz":"文字播放"},"key":"tag"},{"para":{"nameSide":"left","charaName":"{nvzhuName}","text":"[show]好！我会努力提升自己的！[l][hide][cm]"},"key":"text"},{"para":{"cz":"等待"},"key":"tag"},{"para":{"tag":"tag_7"},"key":"tag"},{"para":{"cz":"特效"},"key":"tag"},{"para":{"cz":"音效"},"key":"tag"},{"para":{"cz":"前层立绘消失"},"key":"tag"},{"para":{"trans":false,"alpha":0,"scaleX":1,"y":40,"scaleY":1,"img":"nanzhu_YJbanlian","mirrow":false,"transTime":0,"bright":0.95,"layer":"chara2","x":480},"key":"moveLayer"},{"para":{"cz":"前层背景消失"},"key":"tag"},{"para":{"cz":"当前层背景出现"},"key":"tag"},{"para":{"cz":"当前层立绘出现"},"key":"tag"},{"para":{"trans":false,"alpha":0,"scaleX":1,"y":40,"scaleY":1,"img":"nanzhu_YJmiantan","mirrow":false,"bright":1,"layer":"chara2","x":480},"key":"setLayer"},{"para":{"trans":false,"alpha":1,"scaleX":1,"y":40,"scaleY":1,"img":"nanzhu_YJmiantan","mirrow":false,"transTime":0,"bright":1,"layer":"chara2","x":480},"key":"moveLayer"},{"para":{"trans":false,"alpha":1,"scaleX":1,"y":128,"scaleY":1,"img":"nuli","mirrow":false,"transTime":0,"bright":0.95,"layer":"chara1","x":49},"key":"moveLayer"},{"para":{"cz":"语音播放"},"key":"tag"},{"para":{"cz":"文字播放"},"key":"tag"},{"para":{"nameSide":"right","charaName":"苏子轩","text":"[show]秀场回来，你有什么收获？[l][hide][cm]"},"key":"text"},{"para":{"cz":"等待"},"key":"tag"},{"para":{"tag":"tag_8"},"key":"tag"},{"para":{"cz":"特效"},"key":"tag"},{"para":{"cz":"音效"},"key":"tag"},{"para":{"cz":"前层立绘消失"},"key":"tag"},{"para":{"trans":false,"alpha":0,"scaleX":1,"y":128,"scaleY":1,"img":"nuli","mirrow":false,"transTime":0,"bright":0.95,"layer":"chara1","x":49},"key":"moveLayer"},{"para":{"cz":"前层背景消失"},"key":"tag"},{"para":{"cz":"当前层背景出现"},"key":"tag"},{"para":{"cz":"当前层立绘出现"},"key":"tag"},{"para":{"trans":false,"alpha":1,"scaleX":1,"y":40,"scaleY":1,"img":"nanzhu_YJmiantan","mirrow":false,"transTime":0,"bright":0.95,"layer":"chara2","x":480},"key":"moveLayer"},{"para":{"trans":false,"alpha":0,"scaleX":1,"y":128,"scaleY":1,"img":"jingxii","mirrow":false,"bright":1,"layer":"chara1","x":49},"key":"setLayer"},{"para":{"trans":false,"alpha":1,"scaleX":1,"y":128,"scaleY":1,"img":"jingxii","mirrow":false,"transTime":0,"bright":1,"layer":"chara1","x":49},"key":"moveLayer"},{"para":{"cz":"语音播放"},"key":"tag"},{"para":{"cz":"文字播放"},"key":"tag"},{"para":{"nameSide":"left","charaName":"{nvzhuName}","text":"[show]衣服好漂亮，我也说不出哪里漂亮，但是穿在每个模特身上，就好像会发光，一直吸引你看下去。[l][hide][cm]"},"key":"text"},{"para":{"cz":"等待"},"key":"tag"},{"para":{"tag":"tag_9"},"key":"tag"},{"para":{"cz":"特效"},"key":"tag"},{"para":{"cz":"音效"},"key":"tag"},{"para":{"cz":"前层立绘消失"},"key":"tag"},{"para":{"cz":"前层背景消失"},"key":"tag"},{"para":{"cz":"当前层背景出现"},"key":"tag"},{"para":{"cz":"当前层立绘出现"},"key":"tag"},{"para":{"trans":false,"alpha":1,"scaleX":1,"y":40,"scaleY":1,"img":"nanzhu_YJmiantan","mirrow":false,"transTime":0,"bright":1,"layer":"chara2","x":480},"key":"moveLayer"},{"para":{"trans":false,"alpha":1,"scaleX":1,"y":128,"scaleY":1,"img":"jingxii","mirrow":false,"transTime":0,"bright":0.95,"layer":"chara1","x":49},"key":"moveLayer"},{"para":{"cz":"语音播放"},"key":"tag"},{"para":{"cz":"文字播放"},"key":"tag"},{"para":{"nameSide":"right","charaName":"苏子轩","text":"[show]衣服只是外在包装，作为一个职业的时尚界明星，能够将任意一件衣服随心驾驭，当然这些对你来说，都太早了些，你还要一步步脚踏实地的开始。[l][hide][cm]"},"key":"text"},{"para":{"cz":"等待"},"key":"tag"},{"para":{"tag":"tag_10"},"key":"tag"},{"para":{"cz":"特效"},"key":"tag"},{"para":{"cz":"音效"},"key":"tag"},{"para":{"cz":"前层立绘消失"},"key":"tag"},{"para":{"trans":false,"alpha":0,"scaleX":1,"y":128,"scaleY":1,"img":"jingxii","mirrow":false,"transTime":0,"bright":0.95,"layer":"chara1","x":49},"key":"moveLayer"},{"para":{"cz":"前层背景消失"},"key":"tag"},{"para":{"cz":"当前层背景出现"},"key":"tag"},{"para":{"cz":"当前层立绘出现"},"key":"tag"},{"para":{"trans":false,"alpha":1,"scaleX":1,"y":40,"scaleY":1,"img":"nanzhu_YJmiantan","mirrow":false,"transTime":0,"bright":0.95,"layer":"chara2","x":480},"key":"moveLayer"},{"para":{"trans":false,"alpha":0,"scaleX":1,"y":128,"scaleY":1,"img":"nuli","mirrow":false,"bright":1,"layer":"chara1","x":49},"key":"setLayer"},{"para":{"trans":false,"alpha":1,"scaleX":1,"y":128,"scaleY":1,"img":"nuli","mirrow":false,"transTime":0,"bright":1,"layer":"chara1","x":49},"key":"moveLayer"},{"para":{"cz":"语音播放"},"key":"tag"},{"para":{"cz":"文字播放"},"key":"tag"},{"para":{"nameSide":"left","charaName":"{nvzhuName}","text":"[show]明白了，我一定会好好学习的。[l][hide][cm]"},"key":"text"},{"para":{"cz":"等待"},"key":"tag"},{"para":{"tag":"tag_11"},"key":"tag"},{"para":{"cz":"特效"},"key":"tag"},{"para":{"cz":"音效"},"key":"tag"},{"para":{"cz":"前层立绘消失"},"key":"tag"},{"para":{"cz":"前层背景消失"},"key":"tag"},{"para":{"cz":"当前层背景出现"},"key":"tag"},{"para":{"cz":"当前层立绘出现"},"key":"tag"},{"para":{"trans":false,"alpha":1,"scaleX":1,"y":40,"scaleY":1,"img":"nanzhu_YJmiantan","mirrow":false,"transTime":0,"bright":1,"layer":"chara2","x":480},"key":"moveLayer"},{"para":{"trans":false,"alpha":1,"scaleX":1,"y":128,"scaleY":1,"img":"nuli","mirrow":false,"transTime":0,"bright":0.95,"layer":"chara1","x":49},"key":"moveLayer"},{"para":{"cz":"语音播放"},"key":"tag"},{"para":{"cz":"文字播放"},"key":"tag"},{"para":{"nameSide":"right","charaName":"苏子轩","text":"[show]我给你报了《流行艺术和鉴赏》，可以增强下你的鉴赏能力，下午三点，记得不要迟到……还有这门课的老师对服装相当挑剔，请选择一套你认为当下流行的服装。[l][hide][cm]"},"key":"text"},{"para":{"cz":"等待"},"key":"tag"},{"para":{"tag":"tag_12"},"key":"tag"},{"para":{"cz":"特效"},"key":"tag"},{"para":{"cz":"音效"},"key":"tag"},{"para":{"cz":"前层立绘消失"},"key":"tag"},{"para":{"cz":"前层背景消失"},"key":"tag"},{"para":{"cz":"当前层背景出现"},"key":"tag"},{"para":{"cz":"当前层立绘出现"},"key":"tag"},{"para":{"trans":false,"alpha":1,"scaleX":1,"y":40,"scaleY":1,"img":"nanzhu_YJmiantan","mirrow":false,"transTime":0,"bright":0.95,"layer":"chara2","x":480},"key":"moveLayer"},{"para":{"trans":false,"alpha":1,"scaleX":1,"y":128,"scaleY":1,"img":"nuli","mirrow":false,"transTime":0,"bright":1,"layer":"chara1","x":49},"key":"moveLayer"},{"para":{"cz":"语音播放"},"key":"tag"},{"para":{"cz":"文字播放"},"key":"tag"},{"para":{"nameSide":"left","charaName":"{nvzhuName}","text":"[show]好的[l][hide][cm]"},"key":"text"},{"para":{"cz":"等待"},"key":"tag"}]}