{"script":"300007","des":"普通：热舞晚会主持人","exps":[{"para":{"tag":"tag_1"},"key":"tag"},{"para":{"cz":"特效"},"key":"tag"},{"para":{"cz":"音效"},"key":"tag"},{"para":{"cz":"前层立绘消失"},"key":"tag"},{"para":{"cz":"前层背景消失"},"key":"tag"},{"para":{"cz":"当前层背景出现"},"key":"tag"},{"para":{"y":0,"img":"shiwusuo","bright":1,"alpha":0,"trans":false,"scaleX":1,"layer":"bg","mirrow":false,"scaleY":1,"x":0},"key":"setLayer"},{"para":{"y":0,"img":"shiwusuo","transTime":0,"bright":1,"alpha":1,"trans":false,"scaleX":1,"layer":"bg","mirrow":false,"scaleY":1,"x":0},"key":"moveLayer"},{"para":{"cz":"当前层立绘出现"},"key":"tag"},{"para":{"cz":"语音播放"},"key":"tag"},{"para":{"cz":"文字播放"},"key":"tag"},{"para":{"cz":"等待"},"key":"tag"},{"para":{"tag":"tag_2"},"key":"tag"},{"para":{"cz":"特效"},"key":"tag"},{"para":{"cz":"音效"},"key":"tag"},{"para":{"loop":true,"volume":1,"channel":"bgm","snd":"richang"},"key":"playSound"},{"para":{"cz":"前层立绘消失"},"key":"tag"},{"para":{"cz":"前层背景消失"},"key":"tag"},{"para":{"cz":"当前层背景出现"},"key":"tag"},{"para":{"y":0,"img":"shiwusuo","transTime":500,"bright":0.9,"alpha":1,"trans":true,"scaleX":1,"layer":"bg","mirrow":false,"scaleY":1,"x":0},"key":"moveLayer"},{"para":{"time":500},"key":"wait"},{"para":{"cz":"当前层立绘出现"},"key":"tag"},{"para":{"y":40,"img":"nanzhu_YJmiantan","bright":1,"alpha":0,"trans":true,"scaleX":1,"layer":"chara2","mirrow":false,"scaleY":1,"x":272},"key":"setLayer"},{"para":{"y":40,"img":"nanzhu_YJmiantan","transTime":500,"bright":1,"alpha":1,"trans":true,"scaleX":1,"layer":"chara2","mirrow":false,"scaleY":1,"x":272},"key":"moveLayer"},{"para":{"time":500},"key":"wait"},{"para":{"cz":"语音播放"},"key":"tag"},{"para":{"cz":"文字播放"},"key":"tag"},{"para":{"nameSide":"right","text":"[show]你今天的状态不错。[l][hide][cm]","charaName":"苏子轩"},"key":"text"},{"para":{"cz":"等待"},"key":"tag"},{"para":{"tag":"tag_3"},"key":"tag"},{"para":{"cz":"特效"},"key":"tag"},{"para":{"cz":"音效"},"key":"tag"},{"para":{"cz":"前层立绘消失"},"key":"tag"},{"para":{"cz":"前层背景消失"},"key":"tag"},{"para":{"cz":"当前层背景出现"},"key":"tag"},{"para":{"y":0,"img":"shiwusuo","transTime":0,"bright":0.9,"alpha":1,"trans":false,"scaleX":1,"layer":"bg","mirrow":false,"scaleY":1,"x":0},"key":"moveLayer"},{"para":{"cz":"当前层立绘出现"},"key":"tag"},{"para":{"y":114,"img":"kaixin","bright":1,"alpha":0,"trans":true,"scaleX":1,"layer":"chara1","mirrow":false,"scaleY":1,"x":64},"key":"setLayer"},{"para":{"y":114,"img":"kaixin","transTime":500,"bright":1,"alpha":1,"trans":true,"scaleX":1,"layer":"chara1","mirrow":false,"scaleY":1,"x":64},"key":"moveLayer"},{"para":{"y":40,"img":"nanzhu_YJmiantan","transTime":500,"bright":0.95,"alpha":1,"trans":true,"scaleX":1,"layer":"chara2","mirrow":false,"scaleY":1,"x":480},"key":"moveLayer"},{"para":{"time":500},"key":"wait"},{"para":{"cz":"语音播放"},"key":"tag"},{"para":{"cz":"文字播放"},"key":"tag"},{"para":{"nameSide":"left","text":"[show]真的吗？那我是不是可以接受高级一点的工作了？[l][hide][cm]","charaName":"{nvzhuName}"},"key":"text"},{"para":{"cz":"等待"},"key":"tag"},{"para":{"tag":"tag_5"},"key":"tag"},{"para":{"cz":"特效"},"key":"tag"},{"para":{"cz":"音效"},"key":"tag"},{"para":{"cz":"前层立绘消失"},"key":"tag"},{"para":{"cz":"前层背景消失"},"key":"tag"},{"para":{"cz":"当前层背景出现"},"key":"tag"},{"para":{"cz":"当前层立绘出现"},"key":"tag"},{"para":{"y":114,"img":"kaixin","transTime":0,"bright":1,"alpha":1,"trans":false,"scaleX":1,"layer":"chara1","mirrow":false,"scaleY":1,"x":64},"key":"moveLayer"},{"para":{"y":40,"img":"nanzhu_YJmiantan","transTime":0,"bright":0.95,"alpha":1,"trans":false,"scaleX":1,"layer":"chara2","mirrow":false,"scaleY":1,"x":480},"key":"moveLayer"},{"para":{"cz":"语音播放"},"key":"tag"},{"para":{"cz":"文字播放"},"key":"tag"},{"para":{"cz":"等待"},"key":"tag"},{"para":{"tag":"tag_4"},"key":"tag"},{"para":{"cz":"特效"},"key":"tag"},{"para":{"cz":"音效"},"key":"tag"},{"para":{"cz":"前层立绘消失"},"key":"tag"},{"para":{"y":40,"img":"nanzhu_YJmiantan","transTime":0,"bright":0.95,"alpha":0,"trans":false,"scaleX":1,"layer":"chara2","mirrow":false,"scaleY":1,"x":480},"key":"moveLayer"},{"para":{"cz":"前层背景消失"},"key":"tag"},{"para":{"cz":"当前层背景出现"},"key":"tag"},{"para":{"cz":"当前层立绘出现"},"key":"tag"},{"para":{"y":114,"img":"kaixin","transTime":0,"bright":0.95,"alpha":1,"trans":false,"scaleX":1,"layer":"chara1","mirrow":false,"scaleY":1,"x":64},"key":"moveLayer"},{"para":{"y":40,"img":"nanzhu_YJbanlian","bright":1,"alpha":0,"trans":false,"scaleX":1,"layer":"chara2","mirrow":false,"scaleY":1,"x":480},"key":"setLayer"},{"para":{"y":40,"img":"nanzhu_YJbanlian","transTime":0,"bright":1,"alpha":1,"trans":false,"scaleX":1,"layer":"chara2","mirrow":false,"scaleY":1,"x":480},"key":"moveLayer"},{"para":{"cz":"语音播放"},"key":"tag"},{"para":{"cz":"文字播放"},"key":"tag"},{"para":{"nameSide":"right","text":"[show]怎么？你对现在的工作不满意？[l][hide][cm]","charaName":"苏子轩"},"key":"text"},{"para":{"cz":"等待"},"key":"tag"},{"para":{"tag":"tag_6"},"key":"tag"},{"para":{"cz":"特效"},"key":"tag"},{"para":{"cz":"音效"},"key":"tag"},{"para":{"cz":"前层立绘消失"},"key":"tag"},{"para":{"y":114,"img":"kaixin","transTime":0,"bright":0.95,"alpha":0,"trans":false,"scaleX":1,"layer":"chara1","mirrow":false,"scaleY":1,"x":64},"key":"moveLayer"},{"para":{"cz":"前层背景消失"},"key":"tag"},{"para":{"cz":"当前层背景出现"},"key":"tag"},{"para":{"cz":"当前层立绘出现"},"key":"tag"},{"para":{"y":114,"img":"kuxiao","bright":1,"alpha":0,"trans":false,"scaleX":1,"layer":"chara1","mirrow":false,"scaleY":1,"x":64},"key":"setLayer"},{"para":{"y":114,"img":"kuxiao","transTime":0,"bright":1,"alpha":1,"trans":false,"scaleX":1,"layer":"chara1","mirrow":false,"scaleY":1,"x":64},"key":"moveLayer"},{"para":{"y":40,"img":"nanzhu_YJbanlian","transTime":0,"bright":0.95,"alpha":1,"trans":false,"scaleX":1,"layer":"chara2","mirrow":false,"scaleY":1,"x":480},"key":"moveLayer"},{"para":{"cz":"语音播放"},"key":"tag"},{"para":{"cz":"文字播放"},"key":"tag"},{"para":{"nameSide":"left","text":"[show]没有，我只是表示一下内心的惊喜之情。[l][hide][cm]","charaName":"{nvzhuName}"},"key":"text"},{"para":{"cz":"等待"},"key":"tag"},{"para":{"tag":"tag_7"},"key":"tag"},{"para":{"cz":"特效"},"key":"tag"},{"para":{"cz":"音效"},"key":"tag"},{"para":{"cz":"前层立绘消失"},"key":"tag"},{"para":{"y":40,"img":"nanzhu_YJbanlian","transTime":0,"bright":0.95,"alpha":0,"trans":false,"scaleX":1,"layer":"chara2","mirrow":false,"scaleY":1,"x":480},"key":"moveLayer"},{"para":{"cz":"前层背景消失"},"key":"tag"},{"para":{"cz":"当前层背景出现"},"key":"tag"},{"para":{"cz":"当前层立绘出现"},"key":"tag"},{"para":{"y":114,"img":"kuxiao","transTime":0,"bright":0.95,"alpha":1,"trans":false,"scaleX":1,"layer":"chara1","mirrow":false,"scaleY":1,"x":64},"key":"moveLayer"},{"para":{"y":40,"img":"nanzhu_YJmiantan","bright":1,"alpha":0,"trans":false,"scaleX":1,"layer":"chara2","mirrow":false,"scaleY":1,"x":480},"key":"setLayer"},{"para":{"y":40,"img":"nanzhu_YJmiantan","transTime":0,"bright":1,"alpha":1,"trans":false,"scaleX":1,"layer":"chara2","mirrow":false,"scaleY":1,"x":480},"key":"moveLayer"},{"para":{"cz":"语音播放"},"key":"tag"},{"para":{"cz":"文字播放"},"key":"tag"},{"para":{"nameSide":"right","text":"[show]恩，那这个任务交给你。[l][hide][cm]","charaName":"苏子轩"},"key":"text"},{"para":{"cz":"等待"},"key":"tag"},{"para":{"tag":"tag_8"},"key":"tag"},{"para":{"cz":"特效"},"key":"tag"},{"para":{"cz":"音效"},"key":"tag"},{"para":{"cz":"前层立绘消失"},"key":"tag"},{"para":{"y":114,"img":"kuxiao","transTime":0,"bright":0.95,"alpha":0,"trans":false,"scaleX":1,"layer":"chara1","mirrow":false,"scaleY":1,"x":64},"key":"moveLayer"},{"para":{"cz":"前层背景消失"},"key":"tag"},{"para":{"cz":"当前层背景出现"},"key":"tag"},{"para":{"cz":"当前层立绘出现"},"key":"tag"},{"para":{"y":128,"img":"haoqi","bright":1,"alpha":0,"trans":false,"scaleX":1,"layer":"chara1","mirrow":false,"scaleY":1,"x":49},"key":"setLayer"},{"para":{"y":128,"img":"haoqi","transTime":0,"bright":1,"alpha":1,"trans":false,"scaleX":1,"layer":"chara1","mirrow":false,"scaleY":1,"x":49},"key":"moveLayer"},{"para":{"y":40,"img":"nanzhu_YJmiantan","transTime":0,"bright":0.95,"alpha":1,"trans":false,"scaleX":1,"layer":"chara2","mirrow":false,"scaleY":1,"x":480},"key":"moveLayer"},{"para":{"cz":"语音播放"},"key":"tag"},{"para":{"cz":"文字播放"},"key":"tag"},{"para":{"nameSide":"left","text":"[show]这个是？[l][hide][cm]","charaName":"{nvzhuName}"},"key":"text"},{"para":{"cz":"等待"},"key":"tag"},{"para":{"tag":"tag_9"},"key":"tag"},{"para":{"cz":"特效"},"key":"tag"},{"para":{"cz":"音效"},"key":"tag"},{"para":{"cz":"前层立绘消失"},"key":"tag"},{"para":{"cz":"前层背景消失"},"key":"tag"},{"para":{"cz":"当前层背景出现"},"key":"tag"},{"para":{"cz":"当前层立绘出现"},"key":"tag"},{"para":{"y":128,"img":"haoqi","transTime":0,"bright":0.95,"alpha":1,"trans":false,"scaleX":1,"layer":"chara1","mirrow":false,"scaleY":1,"x":49},"key":"moveLayer"},{"para":{"y":40,"img":"nanzhu_YJmiantan","transTime":0,"bright":1,"alpha":1,"trans":false,"scaleX":1,"layer":"chara2","mirrow":false,"scaleY":1,"x":480},"key":"moveLayer"},{"para":{"cz":"语音播放"},"key":"tag"},{"para":{"cz":"文字播放"},"key":"tag"},{"para":{"nameSide":"right","text":"[show]这个是本市街舞团所举行的热舞晚会的邀请函。[l][hide][cm]","charaName":"苏子轩"},"key":"text"},{"para":{"cz":"等待"},"key":"tag"},{"para":{"tag":"tag_11"},"key":"tag"},{"para":{"cz":"特效"},"key":"tag"},{"para":{"cz":"音效"},"key":"tag"},{"para":{"cz":"前层立绘消失"},"key":"tag"},{"para":{"cz":"前层背景消失"},"key":"tag"},{"para":{"layer":"chara3"},"key":"top"},{"para":{"cz":"当前层背景出现"},"key":"tag"},{"para":{"cz":"当前层立绘出现"},"key":"tag"},{"para":{"y":160,"img":"02gaoxing","bright":1,"alpha":0,"trans":true,"scaleX":1,"layer":"chara3","mirrow":false,"scaleY":1,"x":517.5},"key":"setLayer"},{"para":{"y":160,"img":"02gaoxing","transTime":500,"bright":1,"alpha":1,"trans":true,"scaleX":1,"layer":"chara3","mirrow":false,"scaleY":1,"x":517.5},"key":"moveLayer"},{"para":{"y":40,"img":"nanzhu_YJmiantan","transTime":500,"bright":0.95,"alpha":1,"trans":true,"scaleX":1,"layer":"chara2","mirrow":false,"scaleY":1,"x":270},"key":"moveLayer"},{"para":{"time":500},"key":"wait"},{"para":{"cz":"语音播放"},"key":"tag"},{"para":{"cz":"文字播放"},"key":"tag"},{"para":{"nameSide":"right","text":"[show]这个好！这个好！[l][hide][cm]","charaName":"{jinglingName}"},"key":"text"},{"para":{"cz":"等待"},"key":"tag"},{"para":{"tag":"tag_12"},"key":"tag"},{"para":{"cz":"特效"},"key":"tag"},{"para":{"cz":"音效"},"key":"tag"},{"para":{"cz":"前层立绘消失"},"key":"tag"},{"para":{"y":128,"img":"haoqi","transTime":0,"bright":0.95,"alpha":0,"trans":false,"scaleX":1,"layer":"chara1","mirrow":false,"scaleY":1,"x":49},"key":"moveLayer"},{"para":{"cz":"前层背景消失"},"key":"tag"},{"para":{"cz":"当前层背景出现"},"key":"tag"},{"para":{"cz":"当前层立绘出现"},"key":"tag"},{"para":{"y":128,"img":"waitousikao","bright":1,"alpha":0,"trans":false,"scaleX":1,"layer":"chara1","mirrow":false,"scaleY":1,"x":49},"key":"setLayer"},{"para":{"y":128,"img":"waitousikao","transTime":0,"bright":1,"alpha":1,"trans":false,"scaleX":1,"layer":"chara1","mirrow":false,"scaleY":1,"x":49},"key":"moveLayer"},{"para":{"y":160,"img":"02gaoxing","transTime":0,"bright":0.95,"alpha":1,"trans":false,"scaleX":1,"layer":"chara3","mirrow":false,"scaleY":1,"x":517.5},"key":"moveLayer"},{"para":{"y":40,"img":"nanzhu_YJmiantan","transTime":0,"bright":0.95,"alpha":1,"trans":false,"scaleX":1,"layer":"chara2","mirrow":false,"scaleY":1,"x":270},"key":"moveLayer"},{"para":{"cz":"语音播放"},"key":"tag"},{"para":{"cz":"文字播放"},"key":"tag"},{"para":{"nameSide":"left","text":"[show]街舞团？这是什么？很出名吗？[l][hide][cm]","charaName":"{nvzhuName}"},"key":"text"},{"para":{"cz":"等待"},"key":"tag"},{"para":{"tag":"tag_14"},"key":"tag"},{"para":{"cz":"特效"},"key":"tag"},{"para":{"cz":"音效"},"key":"tag"},{"para":{"cz":"前层立绘消失"},"key":"tag"},{"para":{"y":160,"img":"02gaoxing","transTime":0,"bright":0.95,"alpha":0,"trans":false,"scaleX":1,"layer":"chara3","mirrow":false,"scaleY":1,"x":517.5},"key":"moveLayer"},{"para":{"y":40,"img":"nanzhu_YJmiantan","transTime":0,"bright":0.95,"alpha":0,"trans":false,"scaleX":1,"layer":"chara2","mirrow":false,"scaleY":1,"x":270},"key":"moveLayer"},{"para":{"cz":"前层背景消失"},"key":"tag"},{"para":{"cz":"当前层背景出现"},"key":"tag"},{"para":{"cz":"当前层立绘出现"},"key":"tag"},{"para":{"y":128,"img":"waitousikao","transTime":0,"bright":0.95,"alpha":1,"trans":false,"scaleX":1,"layer":"chara1","mirrow":false,"scaleY":1,"x":49},"key":"moveLayer"},{"para":{"y":160,"img":"20hanxiao","bright":0.95,"alpha":0,"trans":false,"scaleX":1,"layer":"chara3","mirrow":false,"scaleY":1,"x":517.5},"key":"setLayer"},{"para":{"y":160,"img":"20hanxiao","transTime":0,"bright":0.95,"alpha":1,"trans":false,"scaleX":1,"layer":"chara3","mirrow":false,"scaleY":1,"x":517.5},"key":"moveLayer"},{"para":{"y":40,"img":"nanzhu_YJbiyan","bright":1,"alpha":0,"trans":false,"scaleX":1,"layer":"chara2","mirrow":false,"scaleY":1,"x":270},"key":"setLayer"},{"para":{"y":40,"img":"nanzhu_YJbiyan","transTime":0,"bright":1,"alpha":1,"trans":false,"scaleX":1,"layer":"chara2","mirrow":false,"scaleY":1,"x":270},"key":"moveLayer"},{"para":{"cz":"语音播放"},"key":"tag"},{"para":{"cz":"文字播放"},"key":"tag"},{"para":{"nameSide":"right","text":"[show]......[l][hide][cm]","charaName":"苏子轩"},"key":"text"},{"para":{"cz":"等待"},"key":"tag"},{"para":{"tag":"tag_15"},"key":"tag"},{"para":{"cz":"特效"},"key":"tag"},{"para":{"cz":"音效"},"key":"tag"},{"para":{"cz":"前层立绘消失"},"key":"tag"},{"para":{"y":40,"img":"nanzhu_YJbiyan","transTime":0,"bright":1,"alpha":0,"trans":false,"scaleX":1,"layer":"chara2","mirrow":false,"scaleY":1,"x":270},"key":"moveLayer"},{"para":{"cz":"前层背景消失"},"key":"tag"},{"para":{"cz":"当前层背景出现"},"key":"tag"},{"para":{"cz":"当前层立绘出现"},"key":"tag"},{"para":{"y":40,"img":"nanzhu_YJbanlian","bright":1,"alpha":0,"trans":false,"scaleX":1,"layer":"chara2","mirrow":false,"scaleY":1,"x":270},"key":"setLayer"},{"para":{"y":40,"img":"nanzhu_YJbanlian","transTime":0,"bright":1,"alpha":1,"trans":false,"scaleX":1,"layer":"chara2","mirrow":false,"scaleY":1,"x":270},"key":"moveLayer"},{"para":{"cz":"语音播放"},"key":"tag"},{"para":{"cz":"文字播放"},"key":"tag"},{"para":{"nameSide":"right","text":"[show]看来你的课程还需要再学一遍。[l][hide][cm]","charaName":"苏子轩"},"key":"text"},{"para":{"cz":"等待"},"key":"tag"},{"para":{"tag":"tag_16"},"key":"tag"},{"para":{"cz":"特效"},"key":"tag"},{"para":{"cz":"音效"},"key":"tag"},{"para":{"cz":"前层立绘消失"},"key":"tag"},{"para":{"y":128,"img":"waitousikao","transTime":0,"bright":0.95,"alpha":0,"trans":false,"scaleX":1,"layer":"chara1","mirrow":false,"scaleY":1,"x":49},"key":"moveLayer"},{"para":{"y":160,"img":"20hanxiao","transTime":0,"bright":0.95,"alpha":0,"trans":false,"scaleX":1,"layer":"chara3","mirrow":false,"scaleY":1,"x":517.5},"key":"moveLayer"},{"para":{"cz":"前层背景消失"},"key":"tag"},{"para":{"cz":"当前层背景出现"},"key":"tag"},{"para":{"cz":"当前层立绘出现"},"key":"tag"},{"para":{"y":128,"img":"jingxia","bright":1,"alpha":0,"trans":false,"scaleX":1,"layer":"chara1","mirrow":false,"scaleY":1,"x":49},"key":"setLayer"},{"para":{"y":128,"img":"jingxia","transTime":0,"bright":1,"alpha":1,"trans":false,"scaleX":1,"layer":"chara1","mirrow":false,"scaleY":1,"x":49},"key":"moveLayer"},{"para":{"y":160,"img":"11jiaoao","bright":0.95,"alpha":0,"trans":false,"scaleX":1,"layer":"chara3","mirrow":false,"scaleY":1,"x":517.5},"key":"setLayer"},{"para":{"y":160,"img":"11jiaoao","transTime":0,"bright":0.95,"alpha":1,"trans":false,"scaleX":1,"layer":"chara3","mirrow":false,"scaleY":1,"x":517.5},"key":"moveLayer"},{"para":{"y":40,"img":"nanzhu_YJbanlian","transTime":0,"bright":0.95,"alpha":1,"trans":false,"scaleX":1,"layer":"chara2","mirrow":false,"scaleY":1,"x":270},"key":"moveLayer"},{"para":{"cz":"语音播放"},"key":"tag"},{"para":{"cz":"文字播放"},"key":"tag"},{"para":{"nameSide":"left","text":"[show]啊，不用了，我想起来了！[wait=500]这个街舞团是本地最有名的舞团，他们每年都要举行好几次热舞晚会！其中最出名的晚会就是每年7月底的各大舞团竞赛晚会！[l][hide][cm]","charaName":"{nvzhuName}"},"key":"text"},{"para":{"cz":"等待"},"key":"tag"},{"para":{"tag":"tag_18"},"key":"tag"},{"para":{"cz":"特效"},"key":"tag"},{"para":{"cz":"音效"},"key":"tag"},{"para":{"cz":"前层立绘消失"},"key":"tag"},{"para":{"y":40,"img":"nanzhu_YJbanlian","transTime":0,"bright":0.95,"alpha":0,"trans":false,"scaleX":1,"layer":"chara2","mirrow":false,"scaleY":1,"x":270},"key":"moveLayer"},{"para":{"cz":"前层背景消失"},"key":"tag"},{"para":{"cz":"当前层背景出现"},"key":"tag"},{"para":{"cz":"当前层立绘出现"},"key":"tag"},{"para":{"y":128,"img":"jingxia","transTime":0,"bright":0.95,"alpha":1,"trans":false,"scaleX":1,"layer":"chara1","mirrow":false,"scaleY":1,"x":49},"key":"moveLayer"},{"para":{"y":40,"img":"nanzhu_YJbiyan","bright":1,"alpha":0,"trans":false,"scaleX":1,"layer":"chara2","mirrow":false,"scaleY":1,"x":270},"key":"setLayer"},{"para":{"y":40,"img":"nanzhu_YJbiyan","transTime":0,"bright":1,"alpha":1,"trans":false,"scaleX":1,"layer":"chara2","mirrow":false,"scaleY":1,"x":270},"key":"moveLayer"},{"para":{"cz":"语音播放"},"key":"tag"},{"para":{"cz":"文字播放"},"key":"tag"},{"para":{"nameSide":"right","text":"[show]这一关勉强算你过了，快去做准备吧！[l][hide][cm]","charaName":"苏子轩"},"key":"text"},{"para":{"cz":"等待"},"key":"tag"},{"para":{"tag":"tag_17"},"key":"tag"},{"para":{"cz":"特效"},"key":"tag"},{"para":{"cz":"音效"},"key":"tag"},{"para":{"cz":"前层立绘消失"},"key":"tag"},{"para":{"y":128,"img":"jingxia","transTime":0,"bright":0.95,"alpha":0,"trans":false,"scaleX":1,"layer":"chara1","mirrow":false,"scaleY":1,"x":49},"key":"moveLayer"},{"para":{"y":160,"img":"11jiaoao","transTime":0,"bright":0.95,"alpha":0,"trans":false,"scaleX":1,"layer":"chara3","mirrow":false,"scaleY":1,"x":517.5},"key":"moveLayer"},{"para":{"cz":"前层背景消失"},"key":"tag"},{"para":{"cz":"当前层背景出现"},"key":"tag"},{"para":{"cz":"当前层立绘出现"},"key":"tag"},{"para":{"y":114,"img":"jiujie","bright":1,"alpha":0,"trans":false,"scaleX":1,"layer":"chara1","mirrow":false,"scaleY":1,"x":64},"key":"setLayer"},{"para":{"y":114,"img":"jiujie","transTime":0,"bright":1,"alpha":1,"trans":false,"scaleX":1,"layer":"chara1","mirrow":false,"scaleY":1,"x":64},"key":"moveLayer"},{"para":{"y":160,"img":"02gaoxing","bright":0.95,"alpha":0,"trans":false,"scaleX":1,"layer":"chara3","mirrow":false,"scaleY":1,"x":517.5},"key":"setLayer"},{"para":{"y":160,"img":"02gaoxing","transTime":0,"bright":0.95,"alpha":1,"trans":false,"scaleX":1,"layer":"chara3","mirrow":false,"scaleY":1,"x":517.5},"key":"moveLayer"},{"para":{"y":40,"img":"nanzhu_YJbiyan","transTime":0,"bright":0.95,"alpha":1,"trans":false,"scaleX":1,"layer":"chara2","mirrow":false,"scaleY":1,"x":270},"key":"moveLayer"},{"para":{"cz":"语音播放"},"key":"tag"},{"para":{"cz":"文字播放"},"key":"tag"},{"para":{"nameSide":"left","text":"[show]好的，好的！我一定会努力的！[l][hide][cm]","charaName":"{nvzhuName}"},"key":"text"},{"para":{"cz":"等待"},"key":"tag"}]}